{"workflow_name": "NoName", "style": "Normal", "custom_id": "7765c9fd-0b09-4f69-8a63-2bd6601736b4", "topology": [{"name": "t0", "dependencies": [], "template": "harbor.cloudcontrolsystems.cn/workflow/task:latest", "duration": 11, "phase": "None", "node_info": "None", "cpu": 2, "mem": 588321536, "env": {"CPU_CONSUME": "100", "MEMORY_CONSUME": "64"}}, {"name": "t2", "dependencies": ["t0"], "template": "harbor.cloudcontrolsystems.cn/workflow/task:latest", "duration": 16, "phase": "None", "node_info": "None", "cpu": 2, "mem": 724884181, "env": {"CPU_CONSUME": "100", "MEMORY_CONSUME": "64"}}, {"name": "t1", "dependencies": [], "template": "harbor.cloudcontrolsystems.cn/workflow/task:latest", "duration": 25, "phase": "None", "node_info": "None", "cpu": 2, "mem": 908694576, "env": {"CPU_CONSUME": "100", "MEMORY_CONSUME": "64"}}, {"name": "t4", "dependencies": ["t2", "t1"], "template": "harbor.cloudcontrolsystems.cn/workflow/task:latest", "duration": 14, "phase": "None", "node_info": "None", "cpu": 3, "mem": 797720407, "env": {"CPU_CONSUME": "100", "MEMORY_CONSUME": "64"}}, {"name": "t3", "dependencies": ["t1"], "template": "harbor.cloudcontrolsystems.cn/workflow/task:latest", "duration": 20, "phase": "None", "node_info": "None", "cpu": 3, "mem": 1024149189, "env": {"CPU_CONSUME": "100", "MEMORY_CONSUME": "64"}}, {"name": "t5", "dependencies": ["t4", "t3"], "template": "harbor.cloudcontrolsystems.cn/workflow/task:latest", "duration": 14, "phase": "None", "node_info": "None", "cpu": 3, "mem": 659064703, "env": {"CPU_CONSUME": "100", "MEMORY_CONSUME": "64"}}]}